spotify_local/__init__.py
spotify_local/config.py
spotify_local/core.py
spotify_local/utils.py
spotify_local-0.3.2.dist-info/METADATA
spotify_local-0.3.2.dist-info/RECORD
spotify_local-0.3.2.dist-info/WHEEL
spotify_local-0.3.2.dist-info/top_level.txt
